README.md
setup.cfg
setup.py
evaltools/__init__.py
evaltools/logger.py
evaltools/utils.py
evaltools.egg-info/PKG-INFO
evaltools.egg-info/SOURCES.txt
evaltools.egg-info/dependency_links.txt
evaltools.egg-info/requires.txt
evaltools.egg-info/top_level.txt