Metadata-Version: 1.0
Name: evaltools
Version: 0.0
Summary: Simple library to evaluate the performance of python functions.
Home-page: UNKNOWN
Author: Lukas Ewecker
Author-email: lukasewecker@web.de
License: MIT License
Platform: UNKNOWN
